{
  "title": "Somewhere",
  "youtube_id": "7W0m6tDgoag",
  "local_video_url": "",
  "today_expression": {
    "ja": "いつでも そばに いるよ",
    "ko": "언제나 곁에 있어줄게",
    "words": [
      {"ja": "いつでも", "ko": "언제나"},
      {"ja": "そばに", "ko": "곁에"},
      {"ja": "いる", "ko": "있다"},
      {"ja": "よ", "ko": "(강조 표현)"}
    ]
  },
  "lyrics": [
    "ねぇ　どうして　泣いているの",
    "教えて　誰に　打ち明ければ　いいの？",
    "悲しみが　心のドアを叩いたら",
    "その時は　私を　思い出して　欲しい",
    "いつでも　そばに　いるよ",
    "同じ空　見上げてる",
    "どんなに　遠く　離れても",
    "信じて　君のことを",
    "抱きしめて　あげたい",
    "冷たい風に　震える",
    "心が　壊れてしまわぬように",
    "小さな　勇気を　ポケットに",
    "大事に　しまって　歩こう",
    "明日は　きっと　やってくる",
    "君だけの　陽だまりを　連れて"
  ]
}